effectScreenRecorderMaster/__init__.py
effectScreenRecorderMaster/__main__.py
effectScreenRecorderMaster/config_manager.py
effectScreenRecorderMaster/effectScreenRecorderMaster.py
effectScreenRecorderMaster/preview_manager.py
effectScreenRecorderMaster/assets/preview.png
effect_srm-0.1.0.dist-info/LICENSE
effect_srm-0.1.0.dist-info/METADATA
effect_srm-0.1.0.dist-info/WHEEL
effect_srm-0.1.0.dist-info/entry_points.txt
effect_srm-0.1.0.dist-info/top_level.txt
effect_srm-0.1.0.dist-info/RECORD
