Metadata-Version: 2.2
Name: effect-srm
Version: 0.1.0
Summary: Grabador de pantalla con efectos en tiempo real (Sin POSTPROCESADO)
Author-email: Tutos Rive <srmtrg.ser@gmail.com>
License: MIT
Project-URL: Documentation, https://tutosrive.github.io/effect-screen-recorder-master/
Project-URL: Repositorio, https://github.com/tutosrive/effect-screen-recorder-master/
Classifier: License :: OSI Approved :: MIT License
Classifier: Programming Language :: Python :: 3.11
Classifier: Operating System :: Microsoft :: Windows :: Windows 10
Requires-Python: >=3.11.6
License-File: LICENSE
Requires-Dist: customtkinter==5.2.2
Requires-Dist: pillow==11.1.0
Requires-Dist: ffmpeg-python==0.2.0
Requires-Dist: chromologger==0.1.8
